browser_automation/__init__.py
browser_automation/browser_manipulation.py
browser_automation/browser_setup.py
browser_automation/locate_elements.py
browser_automation/os_json_utils.py
browser_automationpy-0.0.2.dist-info/LICENSE.txt
browser_automationpy-0.0.2.dist-info/METADATA
browser_automationpy-0.0.2.dist-info/WHEEL
browser_automationpy-0.0.2.dist-info/top_level.txt
browser_automationpy-0.0.2.dist-info/RECORD
