Metadata-Version: 2.1
Name: browser-automationpy
Version: 0.0.2
Summary: A python project for easily launching custom automated browser to reduce repetitive boring work.
Home-page: https://github.com/chandraveshchaudhari/browser-automationpy
Author: Chandravesh Chaudhari
Author-email: chandraveshchaudhari@gmail.com
Project-URL: Bug Tracker, https://github.com/chandraveshchaudhari/browser-automationpy/issues
Project-URL: Bug Reports, https://github.com/chandraveshchaudhari/browser-automationpy/issues
Project-URL: Say Thanks!, https://saythanks.io/to/chandraveshchaudhari
Project-URL: Source, https://github.com/chandraveshchaudhari/browser-automationpy/
Keywords: browser,automation,selenium,testing,data mining
Classifier: Development Status :: 4 - Beta
Classifier: Topic :: Internet :: WWW/HTTP :: Browsers
Classifier: Intended Audience :: End Users/Desktop
Classifier: Programming Language :: Python :: 3.6
Classifier: License :: OSI Approved :: MIT License
Classifier: Operating System :: OS Independent
Requires-Python: >=3.6
License-File: LICENSE.txt
Requires-Dist: selenium
Requires-Dist: webdriver-manager
